oson/__init__.py
oson/orm_example.py
oson/pson.py
oson-0.0.1.dist-info/LICENSE
oson-0.0.1.dist-info/METADATA
oson-0.0.1.dist-info/WHEEL
oson-0.0.1.dist-info/top_level.txt
oson-0.0.1.dist-info/RECORD
