Metadata-Version: 2.1
Name: oson
Version: 0.0.1
Summary: This is a package for encode/decode python objects with json.
Home-page: https://github.com/wuranxu/oson
Author: woody
Author-email: 619434176@qq.com
License: UNKNOWN
Platform: UNKNOWN
Classifier: License :: OSI Approved :: MIT License
Classifier: Intended Audience :: Developers
Classifier: Operating System :: OS Independent
Classifier: Programming Language :: Python :: 3
Requires-Python: >=3.6
